{
  "main": {
    "id": "ff13853cd880cd70",
    "type": "split",
    "children": [
      {
        "id": "bafc2e9179dde8b7",
        "type": "tabs",
        "children": [
          {
            "id": "8e10d94bfc9ad4b3",
            "type": "leaf",
            "state": {
              "type": "markdown",
              "state": {
                "file": "z_Templates/Plantilla- Facciones.md",
                "mode": "preview",
                "source": true
              }
            }
          },
          {
            "id": "8ec1f778f928c971",
            "type": "leaf",
            "state": {
              "type": "markdown",
              "state": {
                "file": "4.Facciones/La escama plateada.md",
                "mode": "source",
                "source": false
              }
            }
          }
        ],
        "currentTab": 1
      }
    ],
    "direction": "vertical"
  },
  "left": {
    "id": "420676fb70a5ff68",
    "type": "split",
    "children": [
      {
        "id": "68d169e2f47fa8b4",
        "type": "tabs",
        "children": [
          {
            "id": "59369172aaba219c",
            "type": "leaf",
            "state": {
              "type": "file-explorer",
              "state": {
                "sortOrder": "alphabetical"
              }
            }
          },
          {
            "id": "01c245aacb8c2073",
            "type": "leaf",
            "state": {
              "type": "search",
              "state": {
                "query": "dataviewjs",
                "matchingCase": false,
                "explainSearch": false,
                "collapseAll": false,
                "extraContext": false,
                "sortOrder": "alphabetical"
              }
            }
          },
          {
            "id": "55899e3c055c4d95",
            "type": "leaf",
            "state": {
              "type": "bookmarks",
              "state": {}
            }
          }
        ]
      }
    ],
    "direction": "horizontal",
    "width": 300
  },
  "right": {
    "id": "cc70ceb331cfaefc",
    "type": "split",
    "children": [
      {
        "id": "66e141e4c5c2be88",
        "type": "tabs",
        "children": [
          {
            "id": "785ab9631e1f7755",
            "type": "leaf",
            "state": {
              "type": "backlink",
              "state": {
                "file": "4.Facciones/La escama plateada.md",
                "collapseAll": false,
                "extraContext": false,
                "sortOrder": "alphabetical",
                "showSearch": false,
                "searchQuery": "",
                "backlinkCollapsed": false,
                "unlinkedCollapsed": true
              }
            }
          },
          {
            "id": "a5305f3790e19a54",
            "type": "leaf",
            "state": {
              "type": "outgoing-link",
              "state": {
                "file": "4.Facciones/La escama plateada.md",
                "linksCollapsed": false,
                "unlinkedCollapsed": true
              }
            }
          },
          {
            "id": "7ca9bbb8cbaed2db",
            "type": "leaf",
            "state": {
              "type": "tag",
              "state": {
                "sortOrder": "frequency",
                "useHierarchy": true
              }
            }
          },
          {
            "id": "3b4fec93070d724c",
            "type": "leaf",
            "pinned": true,
            "state": {
              "type": "markdown",
              "state": {
                "file": "0.Campañas/0.Campañas.md",
                "mode": "preview",
                "source": false
              },
              "pinned": true
            }
          },
          {
            "id": "2b4290b2a206ded4",
            "type": "leaf",
            "state": {
              "type": "outline",
              "state": {
                "file": "4.Facciones/La escama plateada.md"
              }
            }
          },
          {
            "id": "8c6f6c034f5e85a1",
            "type": "leaf",
            "state": {
              "type": "DICE_ROLLER_VIEW",
              "state": {}
            }
          },
          {
            "id": "b7c59265677dbc4e",
            "type": "leaf",
            "state": {
              "type": "initiative-tracker-view",
              "state": {}
            }
          },
          {
            "id": "ecc03ac9d45600a5",
            "type": "leaf",
            "state": {
              "type": "all-properties",
              "state": {
                "sortOrder": "frequency",
                "showSearch": false,
                "searchQuery": ""
              }
            }
          },
          {
            "id": "36647f2dee74b912",
            "type": "leaf",
            "state": {
              "type": "CALENDARIUM",
              "state": {
                "calendar": "ID_fbd88a383ac8",
                "ephemeral": {
                  "viewState": 1,
                  "displaying": {
                    "year": 783,
                    "month": 0,
                    "day": 7
                  },
                  "displayDayNumber": false,
                  "displayMoons": true
                }
              }
            }
          }
        ],
        "currentTab": 3
      }
    ],
    "direction": "horizontal",
    "width": 300
  },
  "left-ribbon": {
    "hiddenItems": {
      "switcher:Open quick switcher": false,
      "graph:Open graph view": false,
      "canvas:Create new canvas": false,
      "daily-notes:Open today's daily note": false,
      "templates:Insert template": false,
      "command-palette:Open command palette": false,
      "obsidian-leaflet-plugin:Open Leaflet Map": false,
      "templater-obsidian:Templater": false,
      "open-vscode:VSCode": false,
      "initiative-tracker:Initiative Tracker Encounter Builder": false,
      "obsidian-5e-statblocks:Open Creature Pane": false,
      "obsidian42-brat:BRAT": false,
      "calendarium:Open Calendarium": false
    }
  },
  "active": "8ec1f778f928c971",
  "lastOpenFiles": [
    "4.Facciones/4.Facciones.md",
    "4.Facciones/La escama plateada.md",
    "z_Assets/Emblemas/xalemg_silver_dragon_silver_scale_and_a_silver_shield_simple_b31eb386-0346-433f-b4f2-0066f62783de (1).png.crdownload",
    "0.Campañas/0.Campañas.md",
    "3.Lugares/Ust Natha.md",
    "z_Assets/Emblemas/La escama plateada.png",
    "⭐Hub.md",
    "3.Lugares/3.Lugares.md",
    "3.Lugares/Islas Shamal.md",
    "3.Lugares/Crestafria.md",
    "5.NPCs/5.NPCs.md",
    "3.Lugares/Isla de Altalos.md",
    "5.NPCs/Rufus.md",
    "z_Templates/Plantilla- Facciones.md",
    "4.Facciones/Ciudades libres de Adur.md",
    "2.Panteón/Amaunator.md",
    "2.Panteón/Bahamut.md",
    "2.Panteón/Bane.md",
    "2.Panteón/Gruumsh.md",
    "2.Panteón/Karl Brillabomba.md",
    "2.Panteón/Moradin.md",
    "2.Panteón/Mystra.md",
    "2.Panteón/Tiamat.md",
    "2.Panteón/Trithereon.md",
    "2.Panteón/Tyr.md",
    "2.Panteón/Umberlee.md",
    "2.Panteón/Vecna.md",
    "2.Panteón/Adur.md",
    "z_Assets/Emblemas/emblema mancomunidad.png",
    "z_Assets/Arte/Material_Plane.webp",
    "z_Assets/Arte/Material_Plane.webp.crdownload",
    "z_Assets/Arte/infraoscuridad.jpeg",
    "z_Assets/Emblemas/altalos.png",
    "z_Classes/Classes",
    "z_Classes/Options",
    "z_Assets/Misc/PlaceholderImage.png",
    "0.Campañas/El desencadenamiento/Ideas",
    "z_Assets/Emblemas/cnocilio caparazón (1).png",
    "z_Assets/Emblemas/emblema ciudades libres.png",
    "z_Assets/Jugadores/Ainlaoo.jpg"
  ]
}